{"350_100.out": "f ssss pppp eeee gg dddddddd hhh ttttt www nnnn ff ggggg m xxx z c vvvv sss qq ssssss lllll llllll fffffff rrrrrrr jjjjjjj wwwwwww f\n24\nssss ssss vv ffffffff\neeee uu eeee\ndddddddd dddddddd\nttttt ttttt\nf f\nnnnn nnnn\nff ff\nggggg ggggg\nm m\nxxx xxx\nz z\nc w p zzz xxxxxx uuuuu llllllll c hhhh ggg wwww qqqqqqq pp a q\nvvvv qqqqqq vvvv\nsss sss\nqq ss qq\nssssss ssssss aaa\nlllll lllll\nllllll llllll jjjj\nhhh aaaaa rrrrrr hhh\nfffffff rrrrrrrr bbbbbbbb j fffffff\njjjjjjj jjjjjjj\nwwwwwww wwwwwww\nwww v iii\npppp s\n", "350_200.out": "ffffff rrrrrrr hhhh ffffff\n3\nffffff m ggggg xxxxx pppp bbbbbbbb qqq cccccc d jjj x ffffff uu dddd hhh aaaa a llllll j hhhhhhh ssss ll s wwww zzzzz cccc rrrrr gggg ffffffff wwwwww ttttt\nhhhh kkkk o yyyyyyy nnnnnn jjjj cc mmmm mmmmmmmm eeeeee iiiiiii ccccccc ffff bbbbbbb vvv aaaaaa sssss ii gggggggg aaaaaaaa aa tt sssssss uuuuuu zzz xxx rr vvvvvv tttttt qqqqqq hhhh ee rrrrrr e uuuuuuu q oooooo ggggggg vvvvv tttt uuu\nrrrrrrr pppppppp xxxxxxx qq xxxx fffff ssssss lll mm sss kkkkkk kkkkkkkk yy b eeee ttttttt eeeeeee eeeee nnn ooooo aaa lllllll bbbbbb wwwww k dd llllllll iiiiiiii jjjjjj ppppp oooooooo\n", "350_50.out": "gggggggg ccccc ddd ii jjjjjjj uuuu ppp vvv ttttt fffff tt gggggggg\n11\nddd ddd\ngggggggg gggggggg\njjjjjjj jjjjjjj\nccccc ccccc\nvvv vvv\ntt tt\nttttt ttttt\nuuuu uuuu\nppp ppp\nfffff fffff\nii aaaaaa vvvv zzzzzzz gggg l xxxx qqqqqqq a fffffff cccccccc oooooooo ffff w kkkkkkk\n", "351_100.out": "Toccoa Ashington Tiffin Ledbury Woodstock Devizes Ashington Toccoa\n4\nWoodstock Woodstock\nLedbury Ledbury Brackley\nDevizes Muscatine\nToccoa Bisbee\n", "351_200.out": "Toccoa Ashington Tiffin Ledbury Woodstock Devizes Ashington Toccoa\n4\nWoodstock Woodstock\nLedbury Ledbury Brackley\nToccoa Bisbee\nDevizes Muscatine\n", "351_50.out": "Toccoa Ashington Tiffin Ledbury Woodstock Devizes Ashington Toccoa\n4\nWoodstock Woodstock\nLedbury Ledbury Brackley\nToccoa Bisbee\nDevizes Muscatine\n", "352_100.out": "99 4 18 61 3 6 89 44 89 99 35 37 28 37 32 5 19 23 24 1 15 14 15 88 11 13 3 20 3 53 64 85 61 34 7 22 10 79 86 79 98 21 36 37 35 95 9 51 91 31 0 29 78 16 12 81 76 54 41 46 82 50 82 96 68 55 67 92 65 87 88 11 42 59 1 24 23 58 43 17 8 2 33 38 33 48 47 34 61 69 61 3 57 52 56 30 93 39 78 40 19 26 19 45 25 45 72 71 27 71 72 45 19 60 80 76 18 63 16 22 7 84 99 68 90 54 41 56 62 56 52 57 43 17 43 57 3 6 89 99\n50\n0 0\n1 1\n2 2\n3 3\n4 4\n5 5\n6 6\n7 7\n8 8\n9 9\n10 10\n11 11\n12 12\n13 13\n14 14\n15 15\n16 16\n17 17\n18 18\n19 19\n20 20\n21 21\n22 22\n23 23\n24 24\n25 25\n26 26\n27 27\n28 28\n29 29\n30 30\n31 31\n32 32\n33 33\n34 34\n35 35\n36 36\n37 37\n38 38\n39 39\n40 40\n41 41\n42 42\n43 43\n44 44\n45 45\n46 46\n47 47\n48 48\n63 49\n", "352_200.out": "199 24 10 151 48 5 39 29 7 91 12 91 15 62 94 55 3 18 3 55 83 21 59 114 11 20 60 44 166 134 53 163 17 127 25 113 1 105 77 51 160 185 84 32 120 130 35 159 68 63 22 129 19 27 2 71 158 28 197 103 67 13 101 50 123 147 123 183 52 102 45 80 45 102 97 31 97 102 64 88 176 46 47 36 107 106 42 23 117 141 197 161 109 33 40 144 73 144 186 58 192 74 156 86 14 66 30 138 89 149 87 149 121 178 93 56 93 188 38 79 177 103 81 16 145 37 124 119 4 119 78 167 115 171 125 109 57 61 57 108 13 67 34 98 8 65 76 65 8 70 134 154 188 95 189 96 9 96 174 146 142 26 54 150 49 0 49 163 75 163 17 127 110 85 99 139 181 146 142 184 6 72 193 92 43 27 169 122 169 179 169 27 19 129 22 63 143 100 136 171 167 173 74 192 116 192 74 156 86 194 16 182 133 91 137 140 137 91 7 135 132 135 7 29 39 90 39 29 24 199 82 196 190 152 69 152 190 25 113 102 45 102 64 88 176 46 47 129 185 170 187 161 197 172 149 121 178 50 123 183 195 111 195 68 159 194 16 182 35 24 199\n100\n0 0\n1 1\n2 2\n3 3\n4 4\n5 5\n6 6\n7 7\n8 8\n9 9\n10 10\n11 11\n12 12\n13 13\n14 14\n15 15\n16 16\n17 17\n18 18\n19 19\n20 20\n21 21\n22 22\n23 23\n24 24\n25 25\n26 26\n27 27\n28 28\n29 29\n30 30\n31 31\n32 32\n33 33\n34 34\n35 35\n36 36\n37 37\n38 38\n39 39\n40 40\n42 42\n43 43\n44 44\n45 45\n46 46\n47 47\n48 48\n49 49\n50 50\n51 51\n52 52\n53 53\n54 54\n55 55\n56 56\n57 57\n58 58\n59 59\n60 60\n61 61\n62 62\n63 63\n64 64\n65 65\n66 66\n67 67\n68 68\n69 69\n70 70\n71 71\n72 72\n73 73\n74 74\n75 75\n76 76\n77 77\n78 78\n79 79\n80 80\n81 81\n82 82\n83 83\n84 84\n85 85\n86 86\n87 87\n88 88\n89 89\n90 90\n91 91\n92 92\n93 93\n94 94\n95 95\n96 96\n97 97\n98 98\n99 99\n103 41\n", "352_50.out": "49 37 47 1 24 19 34 12 34 19 38 19 13 27 3 11 28 9 14 23 35 10 35 23 14 17 6 37 49\n15\n1 1 18\n3 3\n6 6\n9 9\n10 10 22\n11 11 20\n12 7 12\n13 13\n14 14\n17 17 21\n19 19\n23 4 15 23\n24 8 24\n38 2 16\n27 0 5\n", "356_100.out": "SueJosephGarza CharlesNancySasser PamelaPageBullock WilburnDavidMiller PamelaPageBullock JohnDustinKenny LauraPhilipWinkler AshleyWilliamClarke LauraPhilipWinkler OllieGeorgeSova KarenErmaJensen SueJosephGarza NathanKevinCorathers WilliamGeorgeWilliam IraJimmyYang PamelaPageBullock JohnDustinKenny PamelaPageBullock ChristinaDanaGrant JessicaJohnSpells SueJosephGarza CoraShaneAldana PhyllisJackWilson JohnJoseJudd MelindaKennethAzar DorothyRichardChandl SueJosephGarza\n16\nWilliamGeorgeWilliam WilliamGeorgeWilliam DarnellAliciaPeters\nPamelaPageBullock PamelaPageBullock\nAshleyWilliamClarke BrianRolandAli BrianLuzArce DonaldDoloresKelly AshleyWilliamClarke\nNathanKevinCorathers MaryLindaKirkland NathanKevinCorathers LucyBennyHaag JamesJaredGonzalez MarianLuluDiaz\nJohnDustinKenny JohnDustinKenny\nLauraPhilipWinkler LauraPhilipWinkler\nMelindaKennethAzar MelindaKennethAzar AlfredaKirstenMartin LeroySandraLewis ThomasAnnieRuiz PatriciaBernardBrock KennethShannonGardel SueCourtneyOsgood\nOllieGeorgeSova OllieGeorgeSova\nChristinaDanaGrant ElsieJosephPhelps ChristinaDanaGrant CrystalShermanVida\nWilburnDavidMiller FranciscoFrancesHarr LuisHelenHughes WilburnDavidMiller\nJessicaJohnSpells LillieKathleenCervan JessicaJohnSpells\nPhyllisJackWilson PhyllisJackWilson AnnaKyleChang\nIraJimmyYang IraJimmyYang\nJohnJoseJudd JohnJoseJudd\nKarenErmaJensen KarenErmaJensen MariaChristopherCast\nSueJosephGarza KevinHaroldCyr PaulEvanRichard PaulShaneSoldner\n", "356_200.out": "AlbertFredHaines LeeMillicentTauber JamesJoanneHawn StephenSheldonOrlean EricJamesJuckett ManuelaJoseBailey GeorgeHenryVillar EricTammyScott MarkAnnetteHendrix KentMarylynnPayne WadeSonnyMcbride MarciaWalterKirschma MarkDianeDuchon StevenNeilNguyen HeidiMayJohnson GaryCharlesHudson RosaPatrickYankey FriedaLindaMachesky JanelleEdwardEldridg JimmyFlorTasson JackieSharonScherrer AndrewJeanPinson DonaldYvonneWilliams JoStephenMay SandraJoyceVictorero JeffJohnBruton JuliaMarySmith PeterJosephBarbee LawrenceBarryHadden AlmedaLourdesSimpson EdwardErnestSinger JamesJoanneHawn ZacharyWarrenKarth AlbertFredHaines\n28\nAlbertFredHaines AlbertFredHaines JosephAmandaMullen\nEricJamesJuckett BernicePennyRiddick EricJamesJuckett ElmerDemetriusLark\nEricTammyScott FerdinandLukeJackson EricTammyScott KathleenJoseClark CherylMaryMorgan\nStevenNeilNguyen StevenNeilNguyen HowardKennethCollins\nManuelaJoseBailey ManuelaJoseBailey DenaJewellDavis\nWadeSonnyMcbride WadeSonnyMcbride IsaacGregGargano\nGaryCharlesHudson TommyAmandaMartin GaryCharlesHudson\nJimmyFlorTasson JimmyFlorTasson\nJoStephenMay ClaudeBobbyBaker MistyRobertKing KevinThomasHiggins ThomasEssieEwing JoStephenMay JeremyJamesChavez CraigJohnLard\nPeterJosephBarbee JudyPearlineKaminski GlennaMichaelBorden PeterJosephBarbee\nHeidiMayJohnson JohnBrendaFuller CassandraJaniceGlove MarkAngelaMccloud HeidiMayJohnson\nJackieSharonScherrer JackieSharonScherrer RickyJamesBrumfield DebraJaneFitzgerald\nMarciaWalterKirschma MarciaWalterKirschma BrettDominickSonnier SandraHarryStewart\nMarkDianeDuchon MarthaJackRobinson MarkDianeDuchon\nEdwardErnestSinger KathleenSherryDay EdwardErnestSinger\nLawrenceBarryHadden DeeAmandaBartley CynthiaConnieWright StormyOllieYork LawrenceBarryHadden\nRosaPatrickYankey GeorgeHenryVillar DwainJoeFeldman RosaPatrickYankey\nZacharyWarrenKarth RobinStephenWebster ZacharyWarrenKarth\nKentMarylynnPayne DeniseBrunoWilliam JessicaChristopherHa\nStephenSheldonOrlean JoannCharlieWilkinso KellyJohnnaOles JannaDavidCarranza KevinCharlesEvans\nJuliaMarySmith WilliamDavidGray MichaelMarkHolloway\nJamesJoanneHawn DianeElisePickett\nAlmedaLourdesSimpson RolandGregoryWatson StephenWilliamCoffma JamesJordanZamora JudeJanetHarcourt\nJeffJohnBruton RonaldEdnaArant JohnRichardSmith LynnKennethChavez\nJanelleEdwardEldridg LillianJuanAncona MichaelElizabethWeav TravisMichelleMeller\nAndrewJeanPinson MaryJamesDavila BradleyDeborahSaball AnnDeannaLarzazs\nLeeMillicentTauber GeorgeWilliamJackson PerryJamesBennett\nFriedaLindaMachesky DorisJeffreyBinger EdwardDennisStewart EricTinaPerea\n", "356_50.out": "SusanneJohnBerrios JuanDebbieAllen ClaudiaDavidTaylor LaquitaJohnBrunette RalphClydeMills FernandoLindaWatson StephanieAaronWalker AntonioGeraldBaker GarryDavidKingery DouglasRobertFerkovi RubyLelandCollard HarryNeilFranklin JuliaMollieHernandez DorothyDavidStromme MaryFrankieWomack DougHelenHornbeck DinahCatherineFaulkn MattieBarbaraEkstrom SpencerCourtneyBroth SusanneJohnBerrios\n18\nJuliaMollieHernandez JuliaMollieHernandez\nMattieBarbaraEkstrom MattieBarbaraEkstrom\nSpencerCourtneyBroth SpencerCourtneyBroth\nJuanDebbieAllen JuanDebbieAllen\nDinahCatherineFaulkn DinahCatherineFaulkn\nStephanieAaronWalker StephanieAaronWalker\nLaquitaJohnBrunette LaquitaJohnBrunette\nFernandoLindaWatson FernandoLindaWatson\nDorothyDavidStromme DorothyDavidStromme\nMaryFrankieWomack MaryFrankieWomack\nGarryDavidKingery GarryDavidKingery\nDougHelenHornbeck DougHelenHornbeck\nDouglasRobertFerkovi DouglasRobertFerkovi MonteMonicaLum\nRalphClydeMills RalphClydeMills JorgeHeatherSamuels\nClaudiaDavidTaylor JuliaLindaGordon ClaudiaDavidTaylor\nHarryNeilFranklin HarryNeilFranklin\nAntonioGeraldBaker AntonioGeraldBaker\nRubyLelandCollard RubyLelandCollard\n", "357_100.out": "qgyqjgwlbh njgjyqyhsv gqulqjeire tjcamfqmxd bbtxglggzi yvgxkhagkf hqvifzhbmo yeuzdbmimy wmeeitskjx ajjekwybql sthbsdqlwm sgizgtdhhn czgfnbovhq hrbvyznkmd lgwqodunqt cwlgcuthor hnnlwliezo xsgwbtaqye qgyqjgwlbh\n17\nsthbsdqlwm bzcpozsody sthbsdqlwm kgewtltijq\nwmeeitskjx wmeeitskjx\nsgizgtdhhn sgizgtdhhn ntlhpzyidk\ngqulqjeire fwzkdpfinn somaaudaxm fdbzjhgcmh ysndikwwgh yfvfzingng sngqmldfxu gqulqjeire stxmhuffri bvwklxlwsa tvrzrioagg npffaineub\nczgfnbovhq czgfnbovhq cddppqxsmb iznialmand cynraykzum\najjekwybql smlsmfgyxa wegckoctcp ajjekwybql\nhrbvyznkmd atkqvymdax hrbvyznkmd\ntjcamfqmxd tjcamfqmxd uyirsvqblu vvurcgizpo\nhqvifzhbmo lpopityrof hqvifzhbmo\nlgwqodunqt aruweadnpf lgwqodunqt kmwsevkfov bnfhxmjqzg\nhnnlwliezo hnnlwliezo qlieaqyzel culutarzsm\nnjgjyqyhsv hyficezvgi gdtsmzpvig tdqzbpmftq\ncwlgcuthor feggaeevcb\nbbtxglggzi hpbkyqcejb rzgfaqookt sqlbmrxpwv\nxsgwbtaqye djtmyhmwnn\nyvgxkhagkf xpcqolcpnf\nyeuzdbmimy fnlmocuczk\n", "357_200.out": "dweidxeutk nxiuvgpakn jfjtxukxas dweidxeutk\n3\ndweidxeutk dweidxeutk xwsnmxufqy arrkheyths mnmjklgmnp fuhtgylsov naqyljkxxq cmelcyxenw dzzxropcld rqchbdjiqp wwmcjuetgz ctnsbezpjg cxrfqntbtm elifcmozpf vpghbvlzxd gyjkhdbyvm uqhdcumthr wiwpekzeuz dldiwncohw sjqdgtugly hcvrravrik dfgysrnikx siwbsyuwap vqlbufoinm audojmtlep afkxpktsxw toeqvvzlae efgyvzmusc gmvwahagsy\njfjtxukxas xdmzjapanj tehmqpfdnn pgiiochubt klbefaxnzg cavyunvwuk tzpaywhybw cwexpxaktw nimybvgttg ftrqchqaif hlimwiksjd iqbyvqgkcp wqeazvzkdf rqmdukqpbg bxdnijtmyn gvxfzzmwzk jiowqcrqpz itouxsyevo tofdobbbjt irtbznwvcu gkbqwvqnfu fxejnitkot ulneltboej nmshjtpxad qjjslhkvnr hpqsgalvar akzsqllzsv fwwnyjpwnp okcwuqslme kjgjbkdckc dllzvxpcgk rulcikswsa xtugynuehn lvqqznnzyn cpdpvshtof auonnlthcz\nnxiuvgpakn cowtuqqsll taoimnqdrr pphebmysxy wfybmclpmp lzsvglcvqa aihlvhrjir rwobvahhfa zdiibealli rzqbegeoni gpbaqafhdz tdtlnqnprm cnbqxrvlvl ouzfljsksj fxpsowceqq dlfzngcmgq lgpbgvlzpo vteisghgld rlgdknlxmz zbgxyjmdnm depihfdmjk ivgiotlrrr ienasnqnvt gqwhfeepal bcwzxsuutq sjcwiapdwb hjvmodgwdg kgpqjqjrhc drtcvphibq bqrcwxsyuw wlzaatlgns vtquakjujf xdhiumwdwn kufcwxmspu\n", "357_50.out": "yxgkyomjxk umsvcpgcge riraylfnkc hqzspezetq nlzrbkkyqa frpjxxhdzl lwpniynici atolfdabrg yxgkyomjxk\n8\nhqzspezetq hqzspezetq ercckmiqub dxqtzefxjr uwrlcxuvmr jfpegvbxzj nuhaokcdsy baqrfcdqgq zaleonoxwk\nlwpniynici lwpniynici\natolfdabrg atolfdabrg\numsvcpgcge umsvcpgcge\nnlzrbkkyqa nlzrbkkyqa\nfrpjxxhdzl frpjxxhdzl\nriraylfnkc riraylfnkc\nyxgkyomjxk rblqbbolzt\n", "358_100.out": "Place72 Place2 Place4 Place0 Place10 Place15 Place20 Place30 Place16 Place31 Place34 Place3 Place36 Place41 Place48 Place47 Place52 Place50 Place57 Place1 Place60 Place61 Place0 Place66 Place71 Place75 Place77 Place78 Place3 Place81 Place53 Place87 Place83 Place17 Place72\n30\nPlace2 Place2\nPlace3 Place3\nPlace4 Place4\nPlace10 Place10 Place26 Place56\nPlace15 Place15\nPlace16 Place16\nPlace17 Place17\nPlace20 Place20 Place40\nPlace30 Place30\nPlace31 Place23 Place31 Place86\nPlace34 Place34\nPlace36 Place36\nPlace41 Place41\nPlace47 Place47\nPlace48 Place48 Place98\nPlace50 Place50\nPlace52 Place1 Place43 Place52\nPlace53 Place53\nPlace57 Place57 Place93\nPlace60 Place0 Place19 Place29 Place58 Place59 Place60\nPlace61 Place61\nPlace71 Place71\nPlace75 Place22 Place75\nPlace77 Place77\nPlace78 Place78\nPlace81 Place81\nPlace83 Place83\nPlace87 Place87\nPlace72 Place18 Place33 Place54 Place85 Place88 Place91\nPlace66 Place89\n", "358_200.out": "Place102 Place66 Place159 Place140 Place22 Place88 Place96 Place164 Place24 Place170 Place171 Place175 Place107 Place144 Place51 Place185 Place186 Place102\n17\nPlace96 Place50 Place71 Place96 Place190\nPlace164 Place10 Place116 Place150 Place164 Place181 Place199\nPlace171 Place1 Place3 Place58 Place79 Place100 Place146 Place171\nPlace140 Place16 Place56 Place75 Place76 Place117 Place140\nPlace107 Place28 Place42 Place107 Place137 Place145\nPlace175 Place125 Place147 Place175\nPlace144 Place21 Place55 Place144 Place153 Place166 Place178\nPlace24 Place24 Place95 Place124 Place148 Place168 Place176\nPlace185 Place33 Place108 Place142 Place152 Place155 Place163 Place185\nPlace186 Place8 Place26 Place80 Place82 Place118 Place128 Place186\nPlace22 Place6 Place18 Place20 Place68 Place74 Place81 Place98 Place104 Place139 Place156 Place196 Place198\nPlace66 Place13 Place39 Place41 Place45 Place57 Place77 Place151 Place174 Place197\nPlace159 Place7 Place25 Place32 Place86 Place97 Place114 Place129 Place135 Place172\nPlace51 Place23 Place27 Place47 Place106 Place112 Place120\nPlace102 Place59 Place83\nPlace170 Place72 Place110 Place127 Place182\nPlace88 Place115\n", "358_50.out": "Place23 Place37 Place28 Place43 Place0 Place30 Place6 Place14 Place27 Place7 Place20 Place15 Place40 Place10 Place42 Place8 Place46 Place48 Place23\n18\nPlace0 Place0\nPlace37 Place37\nPlace6 Place6 Place11\nPlace7 Place7\nPlace40 Place40\nPlace8 Place8\nPlace10 Place10\nPlace43 Place43\nPlace42 Place42\nPlace14 Place14\nPlace15 Place15\nPlace46 Place46\nPlace48 Place16 Place17 Place22 Place24 Place25 Place45 Place48\nPlace20 Place20\nPlace23 Place23\nPlace27 Place27\nPlace28 Place28\nPlace30 Place30\n", "359_100.out": "node0 node1 node3 node4 node2 node4 node5 node1 node6 node1 node0 node7 node8 node10 node11 node9 node11 node12 node8 node13 node8 node7 node14 node15 node17 node18 node16 node18 node19 node15 node20 node15 node14 node21 node22 node24 node25 node23 node25 node27 node22 node21 node28 node29 node31 node32 node30 node32 node33 node29 node28 node35 node36 node38 node39 node37 node39 node40 node36 node35 node42 node35 node36 node35 node42 node43 node45 node46 node44 node46 node47 node43 node48 node43 node42 node49 node50 node52 node53 node51 node53 node54 node50 node55 node50 node49 node56 node57 node59 node60 node58 node60 node61 node57 node62 node57 node56 node63 node64 node66 node67 node65 node67 node68 node64 node69 node64 node63 node70 node71 node73 node74 node72 node74 node75 node71 node76 node71 node70 node77 node78 node80 node81 node79 node81 node82 node78 node83 node78 node77 node84 node85 node87 node88 node86 node88 node89 node85 node90 node85 node84 node91 node92 node94 node95 node93 node95 node96 node92 node91 node0\n41\nnode3 node3\nnode5 node5\nnode6 node6\nnode10 node10\nnode12 node12\nnode13 node13\nnode17 node17\nnode19 node19\nnode20 node20\nnode24 node24\nnode27 node27\nnode31 node31 node34\nnode33 node33\nnode38 node38\nnode40 node40\nnode45 node45\nnode47 node47\nnode48 node48\nnode52 node52\nnode54 node54\nnode55 node55\nnode59 node59\nnode61 node61\nnode62 node62\nnode66 node66\nnode68 node68\nnode69 node69\nnode73 node73\nnode75 node75\nnode76 node76\nnode80 node80\nnode82 node82\nnode83 node83\nnode87 node87\nnode89 node89\nnode90 node90\nnode94 node94\nnode96 node96\nnode93 node97\nnode22 node26\nnode37 node41\n", "359_200.out": "node0 node1 node3 node4 node2 node4 node5 node1 node6 node1 node0 node7 node8 node10 node11 node9 node11 node12 node8 node13 node8 node7 node14 node15 node17 node18 node16 node18 node19 node15 node20 node15 node14 node21 node22 node24 node25 node23 node25 node26 node22 node27 node22 node21 node28 node29 node31 node32 node30 node32 node33 node29 node34 node29 node28 node35 node36 node38 node39 node37 node39 node40 node36 node41 node36 node35 node42 node43 node45 node46 node44 node46 node47 node43 node48 node43 node42 node49 node50 node52 node53 node51 node53 node54 node50 node55 node50 node49 node56 node57 node59 node60 node58 node60 node61 node57 node62 node57 node56 node63 node64 node66 node67 node65 node67 node68 node64 node69 node64 node63 node70 node71 node73 node74 node72 node74 node75 node71 node76 node71 node70 node77 node78 node80 node81 node79 node81 node82 node78 node83 node78 node77 node84 node85 node87 node88 node86 node88 node89 node85 node90 node85 node84 node91 node92 node94 node95 node93 node95 node96 node92 node97 node92 node91 node98 node99 node101 node102 node100 node102 node103 node99 node104 node99 node98 node105 node106 node108 node109 node107 node109 node111 node106 node105 node112 node113 node115 node116 node114 node116 node117 node113 node118 node113 node112 node119 node120 node122 node123 node121 node123 node124 node120 node125 node120 node119 node126 node127 node129 node130 node128 node130 node131 node127 node132 node127 node126 node133 node134 node136 node137 node135 node137 node138 node134 node139 node134 node133 node140 node141 node143 node144 node142 node144 node146 node141 node140 node147 node148 node150 node151 node149 node151 node152 node148 node153 node148 node147 node154 node155 node157 node158 node156 node158 node159 node155 node160 node155 node154 node161 node162 node164 node165 node163 node165 node166 node162 node167 node162 node161 node168 node169 node171 node172 node170 node172 node173 node169 node174 node169 node168 node175 node176 node178 node179 node177 node179 node180 node176 node181 node176 node175 node182 node183 node185 node186 node184 node186 node187 node183 node188 node183 node182 node189 node190 node192 node193 node191 node193 node194 node190 node195 node190 node189 node0\n84\nnode3 node3\nnode5 node5\nnode6 node6\nnode10 node10\nnode12 node12\nnode13 node13\nnode17 node17\nnode19 node19\nnode20 node20\nnode24 node24\nnode26 node26\nnode27 node27\nnode31 node31\nnode33 node33\nnode34 node34\nnode38 node38\nnode40 node40\nnode41 node41\nnode45 node45\nnode47 node47\nnode48 node48\nnode52 node52\nnode54 node54\nnode55 node55\nnode59 node59\nnode61 node61\nnode62 node62\nnode66 node66\nnode68 node68\nnode69 node69\nnode73 node73\nnode75 node75\nnode76 node76\nnode80 node80\nnode82 node82\nnode83 node83\nnode87 node87\nnode89 node89\nnode90 node90\nnode94 node94\nnode96 node96\nnode97 node97\nnode101 node101\nnode103 node103\nnode104 node104\nnode108 node108\nnode111 node111\nnode115 node115\nnode117 node117\nnode118 node118\nnode122 node122\nnode124 node124\nnode125 node125\nnode129 node129\nnode131 node131\nnode132 node132\nnode136 node136\nnode138 node138\nnode139 node139\nnode143 node143\nnode146 node146\nnode150 node150\nnode152 node152\nnode153 node153\nnode157 node157\nnode159 node159\nnode160 node160\nnode164 node164\nnode166 node166\nnode167 node167\nnode171 node171\nnode173 node173\nnode174 node174\nnode178 node178\nnode180 node180\nnode181 node181\nnode185 node185\nnode187 node187\nnode188 node188\nnode192 node192\nnode194 node194\nnode195 node195\nnode142 node145\nnode107 node110\n", "359_50.out": "node0 node1 node3 node4 node2 node0 node7 node9 node11 node9 node7 node14 node15 node17 node18 node16 node14 node21 node23 node25 node26 node22 node21 node28 node30 node32 node31 node29 node28 node35 node37 node39 node37 node35 node42 node44 node46 node44 node42 node0\n11\nnode17 node17\nnode26 node26\nnode3 node3\nnode31 node31\nnode32 node33 node34\nnode11 node10 node12 node13\nnode18 node19 node20\nnode46 node45 node47 node48\nnode4 node5 node6\nnode25 node24 node27\nnode39 node38 node40 node41\n", "360_100.out": "gv rp ij ea my ci gv\n5\nea ay dw ea wo yj ve yl fz vf\nij ej hz ec sx fm xm ur ij ef\nrp my zc yo zo rp sc et su\ngv oa il bj cm gu uj gz kx vs bx mb ds\nci bg ho\n", "360_200.out": "qtq tvt dcv tvt udq qfc unk qtq\n5\nqfc ase dkn sfp ooi uxr tmc pjx vaf hxp qfc lxt mbx iuz qlo ahv cjp vsu tnl spp\nqtq pta itg nhk qtq ifc pxs jno qnn wuc wju idl wiq lnv txk yiz plx\nudq xdz xax ptq gup kza pkx vub pwa bai hxo qjm lah egz npu rxi slq zgs udq rju thz brk ahy\ndcv hhe hpb qbe nkx ynq jta fgo zbn tro rut mnv tmd wuf fsl uwp ooc lfh viv wpq orc qls cnv qbj\nunk htv krg cpw zgf eqm bsz nfy uca vlt nhr uoz ili cxu gak zqn ukh thd rwt xos rod\n", "360_50.out": "im yq vo zt cy ns rq qq zw hx kh im\n7\nzt cy sg zt cr ob ak xj xf jm nr vu\nim im\nns ns eo\nhx hx\nyq hf mq yq fe\nvo vo af mm\nqq rq ra ll\n", "361_100.out": "Soda Addison Solano Haviland Anne Fresno Latham Forest Soda\n5\nHaviland Bancroft Burnett Byron Greenwood Haviland Martin Menlo Shasta Summit\nFresno Ajax Arch Bowditch Comstock Cutter Edith Fresno Fulton Haskell Haste Heinz Keeler Lewiston Mabel Overlook Poplar Terrace\nLatham Addison Anne Bret Columbia Colusa Florida High Spring\nSoda Bataan Belrose Forest Hospital Pardee\nSolano Allston Bristol Browning Domingo Eunice Kenilworth Madera Marin Muir Poppy Vermont\n", "362_100.out": "AZ AO CC DO BD BQ CT AL AO AZ\n7\nCT AF BS BX CL CT CY DC DD DV\nBQ AA AN BQ DL\nAL AE AJ AL AV BI BL CR\nCC CC DE DM\nDO AI BO BP CO CP DB DO DQ\nBD AX BD BJ CD CG CK CZ\nAZ AH AO AR AS BE BK BU BW CJ CN CV DT\n", "362_200.out": "FD AI GO AA FA EM FD\n4\nGO AW AZ BO BZ CA CC CO DH DN DP EE EJ ER EW EX FO FY GC GD GO GR GX HB\nEM AJ AU BC BM BT CI CL CS CW DA DC DE DI DZ EK EL EM EN EY FN FS FT FU FV GN GS GZ HC\nFD AF AG AM AT AV AX BG BV CB CK CU DB DM DU EG ES FJ FP GA GF GK GQ HD HH HO\nFA AD AK BA BE BF BK BN BQ CF CG CT DF DK DQ EO ET EZ FI FM FR GP HF HP HR\n", "362_50.out": "BP AZ BW AG BB AB BP\n5\nBW AE BW\nAB AB AK AL AP AV BE BF BK\nAZ AA AF AI AS AX AZ BA BO BQ BU\nBP AT AY BV\nBB AR BN\n", "363_100.out": "30 66 75 67 62 57 41 98 84 6 77 78 52 99 95 30\n15\n66 21 22 23 50 54 55 63 66 68 74 91\n99 8 65 99\n67 26 64 67\n98 3 28 98\n6 6\n41 41\n75 35 75\n77 77 87\n78 78\n84 84\n52 52\n62 62\n57 57\n30 30 86\n95 95\n", "363_200.out": "186 16 90 2 144 186\n5\n144 49 144 150 168 177 188 194\n2 2 5 11 17 45 71 134 138 156 157 162 195 196\n90 14 19 22 30 33 35 61 70 90 107 108 128 140 172 174 183 198\n16 67 79 86 97 121 190\n186 29 32 74 89 104 136 143 178\n", "363_50.out": "38 12 9 35 22 20 6 23 43 33 49 10 18 47 40 42 17 16 44 15 19 26 24 27 38\n23\n6 6\n9 9\n10 10\n12 12\n15 15\n16 16\n17 17\n18 18\n19 19\n20 20\n22 22\n23 23\n24 24\n26 26\n27 27\n33 33\n35 35\n40 40\n42 42\n43 43\n44 44\n47 47\n49 49\n", "364_100.out": "x42 x64 x43 x61 x67 x68 x36 x62 x28 x51 x69 x5 x15 x9 x18 x2 x5 x52 x33 x20 x40 x59 x37 x48 x58 x57 x60 x24 x38 x6 x55 x41 x7 x42\n29\nx2 x2 x3\nx5 x5 x17 x24 x29 x35\nx7 x7\nx9 x9\nx15 x15 x46\nx18 x18\nx20 x20\nx28 x28\nx33 x33\nx36 x36\nx37 x37\nx38 x38\nx40 x40\nx41 x41\nx43 x43\nx48 x48\nx51 x51\nx52 x52\nx55 x55\nx57 x57\nx58 x58\nx59 x59\nx60 x60\nx61 x61\nx62 x62\nx64 x64\nx67 x67\nx68 x68\nx69 x69\n", "364_200.out": "x115 x0 x9 x5 x6 x89 x13 x34 x54 x20 x138 x17 x0 x30 x57 x52 x48 x26 x0 x3 x59 x53 x43 x44 x69 x73 x38 x0 x80 x109 x4 x15 x5 x2 x114 x122 x2 x115\n25\nx4 x4 x21 x32 x33 x40 x84 x92\nx5 x5 x130\nx9 x9 x76 x108\nx138 x138\nx13 x13\nx15 x15\nx17 x17\nx20 x20 x75 x124\nx26 x26 x58\nx34 x34\nx38 x38\nx43 x43 x81 x98\nx44 x44 x50 x61\nx48 x16 x27 x48\nx52 x52 x106\nx53 x53 x62 x94 x127\nx54 x54 x82 x136\nx57 x57 x74\nx59 x59 x71 x111\nx69 x69\nx73 x11 x73 x103\nx89 x64 x89\nx109 x41 x83 x109 x125\nx114 x91 x114 x128\nx122 x122\n", "364_50.out": "a b c d e f g h i j k l m n o p q r s t u v w x w v u t s r q p o n m l k j i h g f e d c b a\n13\na a\nc c\ne e\ng g\ni i\nk k\nm m\no o\nq q\nr r\nt t\nv v\nx x y\n", "365_100.out": "Cleresmith Whitby Bothensborough Chippingwood Sodmersmith Chedlake Ketterwold Milditch Wydon Edgney Basfield Whitseyborough Todderworth Warrerbage Durblechester Dribbasborne Hanworth Ellingey Sunderbrough Chillerlow Eggerrensling Hannerworth Waltcombe Dribbinggrove Pendrenslake Cheddlesport Pendton Elfield Warblesdown Wolvingrethorne Cammingbury Soddenreey Blanden Egwood Skelcastle Cannerrebeck Ciside Hartrenslow Cammenenwich Enderavon Pemhampton Reddenwell Suddlebrough Pendingstoke Stainsdenwold Reddentree Ashworth Cannenringwell Elmsbrook Chilcompcester Hanscombe Watchmanshead Chippenden Camsdenden Rockhead Bootworth Dribbingenborne Dribside Ribney Wendlemerford Hamditch Wetley Bursted Toddendport Nortlake Eggenditch Nortlake Toddendport Bursted Hamditch Wendlemerford Dribside Dribbingenborne Bootworth Rockhead Camsdenden Chippenden Watchmanshead Hanscombe Chilcompcester Elmsbrook Cannenringwell Ashworth Stainsdenwold Pendingstoke Suddlebrough Reddenwell Pemhampton Enderavon Hartrenslow Ciside Cannerrebeck Skelcastle Egwood Blanden Cammingbury Wolvingrethorne Warblesdown Elfield Pendton Cheddlesport Dribbinggrove Waltcombe Hannerworth Eggerrensling Chillerlow Sunderbrough Hanworth Dribbasborne Durblechester Warrerbage Todderworth Whitseyborough Edgney Wydon Milditch Ketterwold Chedlake Sodmersmith Bothensborough Whitby Cleresmith\n27\nChippingwood Chippingwood\nKetterwold Ketterwold\nMilditch Milditch\nBasfield Basfield\nWarrerbage Warrerbage\nDurblechester Durblechester\nEllingey Ellingey\nEggerrensling Eggerrensling\nHannerworth Hannerworth\nPendrenslake Pendrenslake\nElfield Elfield\nWarblesdown Warblesdown\nSoddenreey Soddenreey\nSkelcastle Skelcastle\nCannerrebeck Cannerrebeck\nCammenenwich Cammenenwich\nReddenwell Reddenwell\nSuddlebrough Suddlebrough\nReddentree Reddentree\nElmsbrook Elmsbrook\nChilcompcester Chilcompcester\nRockhead Rockhead\nBootworth Bootworth\nRibney Ribney\nWetley Wetley\nCleresmith Warringwood\nChippenden Shrivden\n", "365_200.out": "Wolney Braindlemoor Horndleside Reddingringey Sodden Nortditch Sodditch Brombrough Hamwich Hammensmith Rotsted Wendlethorne Chipcester Ketthorne Southcompmere Bromwich Stapseyden Prestlake Sistanwick Boothingtree Reddingbourne Edgfield Hannensworth Watchsmith Endlesthorne Alddlesbasbridge Boothingwick Rockdenport Hampenlake Hanbasside Bootherbersted Wendlerewick Dribbinglow Rockenborough Ribbendhead Toddlenell Egmanston Blanavon Ennell Wolden Horslake Alfcastle Brackavon Wycombe Meley Sundlecombe Chedcastle Basserchester Cannell Reddennell Camsreborough Braindlemere Endingey Ellensbrough Eggermoor Cheddenwang Sudhead Pemsdown Wencester Windlesseywang Cirercompsted Pendlesbascastle Endcastle Marlborne Pendlesford Wolverbury Whitborough Camhampton Emthorne Elmerdown Skelling Chilworth Wolbourne Suddendmansavon Braddlesreport Farnsmerbeck Marlringlake Hammingreport Camsmere Burglesbrook Soddlesbasbourne Eghampton Braddleswick Sismith Hammermere Clereshot Worringcompgrove Alddlesenbage Horndlehampton Chelmsbertree Falrensavon Suddingney Hannerley Toddleborne Kettenwell Sundlesborne Staindlemansavon Pendnell Chilmermere Penswick Tiphampton Ketworth Ciringover Aldlow Cammertree Reddlebershot Candleseyney Elsmith Suddendwell Sudderbage Camsted Sirengrove Worglesmernell Shrivgrove Sodham Durrenslow Bootbeck Flitcompwold Sunsseybrook Camtree Reddlesley Hansside Chippingchester Ribblesremoor Worrersted Skellerbury Rothensden Wychringden Ensdown Prestwood Chedwick Dribberbrough Emsbrook Melborne Camling Sudderwick Shaftport Chelmenthorne Falbaswood Siringbrook Leatherberlake Skellingbaswold Skellingmansgrove Elringlow Egwich Tippenside Wolvingborne Chilhall Wolvingborne Cambenscombe Wolvingborne Tippenside Egwich Skellingmansgrove Skellingbaswold Siringbrook Falbaswood Shaftport Sudderwick Camling Melborne Dribberbrough Chedwick Ensdown Wychringden Rothensden Skellerbury Ribblesremoor Chippingchester Reddlesley Camtree Sunsseybrook Flitcompwold Durrenslow Sodham Worglesmernell Sirengrove Camsted Sudderbage Elsmith Candleseyney Cammertree Aldlow Ciringover Ketworth Penswick Chilmermere Staindlemansavon Sundlesborne Kettenwell Toddleborne Suddingney Falrensavon Horndlehampton Alddlesenbage Worringcompgrove Clereshot Sismith Braddleswick Soddlesbasbourne Burglesbrook Camsmere Hammingreport Farnsmerbeck Braddlesreport Wolbourne Chilworth Skelling Elmerdown Camhampton Whitborough Pendlesford Marlborne Endcastle Pendlesbascastle Windlesseywang Wencester Sudhead Cheddenwang Eggermoor Ellensbrough Braindlemere Camsreborough Cannell Basserchester Chedcastle Sundlecombe Wycombe Brackavon Horslake Wolden Ennell Blanavon Toddlenell Ribbendhead Dribbinglow Wendlerewick Bootherbersted Hanbasside Rockdenport Boothingwick Endlesthorne Watchsmith Hannensworth Edgfield Boothingtree Sistanwick Stapseyden Bromwich Southcompmere Ketthorne Wendlethorne Rotsted Hamwich Brombrough Sodditch Nortditch Reddingringey Horndleside Wolney\n55\nStaindlemansavon Staindlemansavon\nBraindlemoor Braindlemoor\nSodden Sodden\nBrombrough Brombrough\nHamwich Hamwich\nTiphampton Tiphampton\nAldlow Aldlow\nCammertree Cammertree\nChipcester Chipcester\nBromwich Bromwich\nStapseyden Stapseyden\nSuddendwell Suddendwell\nSirengrove Sirengrove\nWorglesmernell Worglesmernell\nReddingbourne Reddingbourne\nWatchsmith Watchsmith\nEndlesthorne Endlesthorne\nBootbeck Bootbeck\nCamtree Camtree\nReddlesley Reddlesley\nHampenlake Hampenlake\nWendlerewick Wendlerewick\nDribbinglow Dribbinglow\nWorrersted Worrersted\nWychringden Wychringden\nEnsdown Ensdown\nEgmanston Egmanston\nWolden Wolden\nHorslake Horslake\nEmsbrook Emsbrook\nSudderwick Sudderwick\nShaftport Shaftport\nMeley Meley\nBasserchester Basserchester\nCannell Cannell\nLeatherberlake Leatherberlake\nElringlow Elringlow\nChilhall Chilhall\nEndingey Endingey\nCheddenwang Cheddenwang\nSudhead Sudhead\nCirercompsted Cirercompsted\nMarlborne Marlborne\nPendlesford Pendlesford\nEmthorne Emthorne\nChilworth Chilworth\nWolbourne Wolbourne\nMarlringlake Marlringlake\nBurglesbrook Burglesbrook\nSoddlesbasbourne Soddlesbasbourne\nHammermere Hammermere\nAlddlesenbage Alddlesenbage\nHorndlehampton Horndlehampton\nHannerley Hannerley\nSundlesborne Sundlesborne\n", "365_50.out": "Egbertree Emsham Burrerchester Elmey Watchwang Todderbrough Ciringsmith Rotling Ketley Clerelow Blanhead Shaftgrove Soddleney Egginghall Egmansdown Emsling Camborough Cleremere Fulover Worborough Candlesstanling Chipmerbrook Leatherlow Tipdown Leatherlow Chipmerbrook Candlesstanling Worborough Fulover Cleremere Camborough Emsling Egmansdown Egginghall Soddleney Shaftgrove Blanhead Clerelow Marlseybrough Ketley Rotling Ciringsmith Todderbrough Watchwang Elmey Skelhampton Burrerchester Emsham Egbertree\n12\nSkelhampton Skelhampton\nTodderbrough Todderbrough\nTipdown Tipdown Sidensmith\nCiringsmith Ciringsmith\nMarlseybrough Marlseybrough\nShaftgrove Shaftgrove\nSoddleney Soddleney\nCleremere Cleremere\nFulover Fulover\nCandlesstanling Falrensbury\nEgmansdown Reddledenthorne\nEgbertree Bootherlow\n", "366_100.out": "Warfield Basringney Skelling Hammerringey Elbury Fulbourne Stainbrough Worberbrook Bothingney Pendingbrook Suddlecastle Pendingbrook Tipwick Ashborne Blandlebage Abberhampton Suddleover Chedtree Siringwang Windling Dribblewick Skellingden Horstlescompstoke Rotcombe Worhall Dribbingworth Leatherbleside Ketsmith Ashfield Sundlerensford Wargleentree Fulbage Millendon Elmswang Dribcastle Falport Suddlecombe Ellingreham Chelmstanwell Brackcompwang Chilbury Hammenshead Bastleseyham Dartseyworth Chedderrenswich Basringney Skelling Suddleborne Falport Cicombe Todtree Cannerthorne Tipwick Pendingbrook Chiphead Elcompbridge Cammerrensmoor Blandlebage Cammerwich Faldingney Cannerthorne Warfield\n32\nSuddlecastle Suddlecastle\nChedtree Chedtree\nAshfield Ashfield\nEllingreham Ellingreham\nSuddleover Suddleover Sudsmith\nWorberbrook Worberbrook\nWarfield Warfield Ketport\nWindling Windling\nLeatherbleside Leatherbleside\nCammerrensmoor Cammerrensmoor Wyborne\nTipwick Burglebrough Tipwick Hannenmanswick Southbasport Hamsling\nChelmstanwell Chelmstanwell\nHorstlescompstoke Horstlescompstoke\nPendingbrook Whitchester Pendingbrook\nChiphead Chiphead\nCicombe Cicombe\nSkellingden Barndberbrough Skellingden\nBrackcompwang Chilbury Brackcompwang\nDribbingworth Dribbingworth\nTodtree Todtree\nBastleseyham Bastleseyham\nChedderrenswich Soddlewick Chippingsted Chedderrenswich\nHammerringey Hammerringey Northall\nAshborne Ashborne\nFalport Suddleborne Botherseyworth Pendlewood Stainbrough Falport\nWorhall Worhall\nSiringwang Siringwang\nMillendon Millendon\nBasringney Basringney\nSuddlecombe Cambingstoke Suddlecombe\nSkelling Skelling\nAbberhampton Elmansham\n", "366_200.out": "Whitgrove Stafcombe Worhall Hampingworth Worford Reddendeney Wychchester Barndlesborough Whitgrove\n4\nWhitgrove Emmerley Rothendcombe Leatherport Durbrook Hampingcastle Whitgrove Wycastle Bothenhall Hamwold Farnditch Southmere Farndlesover Bursmith Melwood Tippingbage Faldenhall Endingnell Todhampton\nWychchester Staplow Wetsmith Bastlebury Sodport Sirenshall Alfmere Skellenshot Eley Abcester Tippenbrook Dartden Chedworth Watchlake Endleberey Sundlethorne Enderbeck Penby Casbrook Abglewold Wychchester Cannerthorne Southbury Waltbeck Wethampton Staincombe Sodberling Marlcester Toddenmoor Marlbrook Redcombe\nWorford Hampingworth Horsnell Boothingmanstree Blansbrook Falderseythorne Elside Stapbrough Tippendham Basditch Ketchester Dribberham Candleswick Whitringlake Egsted Sundendford Ellerbridge Ketnell Worford Horstleover Skelberden Wolley Rotherlow\nWorhall Prestwick Worhall Nortwell Wetwick Worrenberwang Sifield Bromstanham Falworth Dribblecombe Egmerhampton Tipstoke Rothingcombe Reddendeney Shaftborough Siavon Cihead Botbeck Bootwick Suddenmoor Milthorne Clereennell Ribberrenston Suddingover Skellingover Abgleham Wendleringdown Hampingbascombe Siey Bothenton Wychcompwold\n", "366_50.out": "Hamsbourne Sundlechester Melcompton Pemstree Botherstanport Leatherblesley Sodderrenshead Egginglow Burrerlake Shaftthorne Camhampton Enderton Dribstoke Endbeck Dribstoke Rocklow Skelgrove Warrewick Skelgrove Prestbourne Sunderborough Ciley Sunderborough Prestbourne Botherstanport Leatherblesley Suddingbeck Candlesdon Boothenrensborough Redderwold Horscompborne Chipfield Hamsbourne\n14\nChipfield Chipfield Hamperrehampton Cammercastle Chipsted\nLeatherblesley Leatherblesley Camswich\nPrestbourne Prestbourne\nCandlesdon Candlesdon Boothenrensborough\nWarrewick Warrewick\nSodderrenshead Sodderrenshead\nCamhampton Enderton Hartberbury Camhampton\nShaftthorne Shaftthorne Sudbage\nCiley Ciley Sunderborough Rotmerby\nRocklow Rocklow Cimansbrough\nBotherstanport Wolvencester\nEndbeck Melshot\nMelcompton Sundlechester\nEgginglow Chilringfield\n"}